secScraper/Filing metrics.py
secScraper/Load_MasterDictionary.py
secScraper/__init__.py
secScraper/csv_to_postgres.py
secScraper/display.py
secScraper/ec2_scraping.py
secScraper/main_new_scores.py
secScraper/metrics.py
secScraper/parser.py
secScraper/post_processing.py
secScraper/postgres.py
secScraper/pre_processing.py
secScraper/processing.py
secScraper/qtrs.py
secScraper-0.0.60.dist-info/LICENSE
secScraper-0.0.60.dist-info/METADATA
secScraper-0.0.60.dist-info/WHEEL
secScraper-0.0.60.dist-info/top_level.txt
secScraper-0.0.60.dist-info/RECORD
