Metadata-Version: 2.1
Name: secScraper
Version: 0.0.60
Summary: Library for Insight project
Home-page: https://github.com/AlexBdx/sec_scrapper/tree/master/sec_scrapper
Author: Alex Bondoux
Author-email: alexandre.bdx@gmail.com
License: UNKNOWN
Platform: UNKNOWN
Classifier: Programming Language :: Python :: 3
Classifier: License :: OSI Approved :: GNU General Public License v3 (GPLv3)
Classifier: Operating System :: POSIX :: Linux
